kallyai_cli/__init__.py
kallyai_cli-1.0.2.dist-info/METADATA
kallyai_cli-1.0.2.dist-info/WHEEL
kallyai_cli-1.0.2.dist-info/entry_points.txt
kallyai_cli-1.0.2.dist-info/licenses/LICENSE
kallyai_cli-1.0.2.dist-info/RECORD
