Metadata-Version: 2.4
Name: kallyai-cli
Version: 1.0.2
Summary: CLI for KallyAI - AI phone assistant that makes calls to businesses
Project-URL: Homepage, https://kallyai.com
Project-URL: Documentation, https://github.com/KallyAI/kallyai-cli
Project-URL: Repository, https://github.com/KallyAI/kallyai-cli
Project-URL: Issues, https://github.com/KallyAI/kallyai-cli/issues
Author-email: KallyAI <support@kallyai.com>
License: Kally Intelligence, Inc. Software License Agreement
License-File: LICENSE
Keywords: ai,appointment,assistant,calls,cli,kallyai,phone,reservation
Classifier: Development Status :: 4 - Beta
Classifier: Environment :: Console
Classifier: Intended Audience :: Developers
Classifier: Intended Audience :: End Users/Desktop
Classifier: License :: Other/Proprietary License
Classifier: Operating System :: OS Independent
Classifier: Programming Language :: Python :: 3
Classifier: Programming Language :: Python :: 3.10
Classifier: Programming Language :: Python :: 3.11
Classifier: Programming Language :: Python :: 3.12
Classifier: Programming Language :: Python :: 3.13
Classifier: Topic :: Communications :: Telephony
Classifier: Topic :: Utilities
Requires-Python: >=3.10
Requires-Dist: httpx>=0.25.0
